README.md
faasconverter
setup.cfg
setup.py
faas_converter/faasconverter.py
faas_converter.egg-info/PKG-INFO
faas_converter.egg-info/SOURCES.txt
faas_converter.egg-info/dependency_links.txt
faas_converter.egg-info/top_level.txt