Metadata-Version: 1.1
Name: faas-converter
Version: 0.0.3
Summary: Function as a service converter
Home-page: https://github.com/walter-bd/faas-converter
Author: Walter Benitez
Author-email: walterbenitez7@gmail.com
License: Apache 2.0
Download-URL: https://github.com/walter-bd/faas-converter/0.3.tar.gz
Keywords: cloud faas serverless functions
Platform: UNKNOWN
Classifier: Development Status :: 2 - Pre-Alpha
Classifier: Environment :: Console
Classifier: Intended Audience :: Science/Research
Classifier: License :: OSI Approved :: Apache Software License
Classifier: Programming Language :: Python :: 3
Classifier: Topic :: Internet :: WWW/HTTP :: WSGI :: Middleware
